commandtoolutils/__init__.py
commandtoolutils/commandtoolutils.py
menu_utils/__init__.py
menu_utils/menu_utils.py
menutools/__init__.py
menutools/menutools.py
tests/__init__.py
tests/example.py
tests/tests.py
commandtoolutils-0.1.dist-info/LICENSE
commandtoolutils-0.1.dist-info/METADATA
commandtoolutils-0.1.dist-info/WHEEL
commandtoolutils-0.1.dist-info/top_level.txt
commandtoolutils-0.1.dist-info/RECORD
