Metadata-Version: 2.1
Name: commandtoolutils
Version: 0.1
Summary: A featherlight utility package for creating interactive command line tools
Home-page: https://github.com/jobordu/menu_utils
Author: Jonathan Borduas
Classifier: Programming Language :: Python :: 3
Classifier: License :: OSI Approved :: MIT License
Classifier: Operating System :: OS Independent
License-File: LICENSE
Requires-Dist: termcolor
Requires-Dist: coverage
Requires-Dist: twine
Requires-Dist: gitignore-parser
Requires-Dist: timeout-decorator
Requires-Dist: wheel
Requires-Dist: keyring
